src/combinational/counter_4bit.v
module counter_4bit (
    input        clk,      // 时钟（上升沿触发）
    input        rst_n,    // 同步复位（低电平有效）
    input        en,       // 计数使能（高电平有效）
    output reg [3:0] cnt,  // 4位计数值
    output reg   cout      // 溢出标志（高电平1个时钟周期）
);

// 同步计数逻辑
always @(posedge clk) begin
    if (!rst_n) begin  // 复位：计数清零，溢出标志置0
        cnt <= 4'd0;
        cout <= 1'b0;
    end else if (en) begin  // 使能时计数
        if (cnt == 4'd15) begin  // 计数到最大值，溢出
            cnt <= 4'd0;
            cout <= 1'b1;
        end else begin  // 未到最大值，正常计数
            cnt <= cnt + 4'd1;
            cout <= 1'b0;
        end
    end else begin  // 未使能，保持当前值
        cnt <= cnt;
        cout <= 1'b0;
    end
end

endmodule

tb/combinational/tb_counter_4bit.sv
module tb_counter_4bit;
    // 激励信号（reg类型）
    reg clk;
    reg rst_n;
    reg en;
    // 响应信号（wire类型）
    wire [3:0] cnt;
    wire cout;

    // 1. 实例化被测模块（DUT）
    counter_4bit dut (
        .clk(clk),
        .rst_n(rst_n),
        .en(en),
        .cnt(cnt),
        .cout(cout)
    );

    // 2. 生成时钟（50MHz，周期20ns）
    initial begin
        clk = 1'b0;
        forever #10 clk = ~clk;  // 每10ns翻转一次，周期20ns
    end

    // 3. 编写测试用例（激励序列）
    initial begin
        // 初始化：复位
        rst_n = 1'b0;
        en = 1'b0;
        #20;  // 等2个时钟周期（让复位生效）

        // 场景1：复位释放，不使能（计数应保持0）
        rst_n = 1'b1;
        en = 1'b0;
        #40;  // 等2个时钟周期
        if (cnt != 4'd0) $error("场景1失败：不使能时计数应保持0");

        // 场景2：使能计数（从0计到15，共16个时钟周期）
	@(posedge clk);
        en = 1'b1;
        #300;  // 16个周期 × 20ns = 320ns
        if (cnt != 4'd15) $error("场景2失败：计数未到15");

        // 场景3：继续计数，触发溢出（15→0，同时cout置1）
        #20;  // 再等1个时钟周期
        if (cnt != 4'd0 || cout != 1'b1) $error("场景3失败：溢出时未清零或无cout");

        // 场景4：溢出后继续计数（0→1，cout置0）
        #20;
        if (cnt != 4'd1 || cout != 1'b0) $error("场景4失败：溢出后计数未加1或cout未置0");

        // 结束仿真
        $display("所有测试场景执行完成！");
        $finish;
    end

    // 4. 加SVA断言（检查时序正确性：只有clk上升沿，cnt才会变）
    assert property (@(posedge clk) $stable(cnt) || en) 
    else $error("断言失败：非使能时cnt被修改");

    // 5.  dump波形（供GTKWave查看）
    initial begin
        $dumpfile("waves/tb_counter_4bit.vcd");
        $dumpvars(0, tb_counter_4bit);
    end

endmodule

sim/waves/tb_counter_4bit.vcd
$date
	Sun Sep 21 16:34:29 2025
$end
$version
	Icarus Verilog
$end
$timescale
	1s
$end
$scope module tb_counter_4bit $end
$var wire 1 ! cout $end
$var wire 4 " cnt [3:0] $end
$var reg 1 # clk $end
$var reg 1 $ en $end
$var reg 1 % rst_n $end
$scope module dut $end
$var wire 1 # clk $end
$var wire 1 $ en $end
$var wire 1 % rst_n $end
$var reg 4 & cnt [3:0] $end
$var reg 1 ! cout $end
$upscope $end
$upscope $end
$enddefinitions $end
$comment Show the parameter values. $end
$dumpall
$end
#0
$dumpvars
bx &
0%
0$
0#
bx "
x!
$end
#10
0!
b0 "
b0 &
1#
#20
0#
1%
#30
1#
#40
0#
#50
1#
#60
0#
#70
b1 "
b1 &
1$
1#
#80
0#
#90
b10 "
b10 &
1#
#100
0#
#110
b11 "
b11 &
1#
#120
0#
#130
b100 "
b100 &
1#
#140
0#
#150
b101 "
b101 &
1#
#160
0#
#170
b110 "
b110 &
1#
#180
0#
#190
b111 "
b111 &
1#
#200
0#
#210
b1000 "
b1000 &
1#
#220
0#
#230
b1001 "
b1001 &
1#
#240
0#
#250
b1010 "
b1010 &
1#
#260
0#
#270
b1011 "
b1011 &
1#
#280
0#
#290
b1100 "
b1100 &
1#
#300
0#
#310
b1101 "
b1101 &
1#
#320
0#
#330
b1110 "
b1110 &
1#
#340
0#
#350
b1111 "
b1111 &
1#
#360
0#
#370
1!
b0 "
b0 &
1#
#380
0#
#390
0!
b1 "
b1 &
1#
#400
0#
#410
b10 "
b10 &
1#
