src/combinational/half_adder.v
// 1位半加器（Half Adder）：无进位输入，仅计算两个1位二进制数的和与进位
module half_adder (
    input  wire A,    // 输入1：1位二进制数
    input  wire B,    // 输入2：1位二进制数
    output wire S,    // 输出：和（Sum）
    output wire Cout  // 输出：进位（Carry Out）
);

// 组合逻辑实现：无需always块，直接用assign描述
assign S    = A ^ B;  // 和 = A异或B（不同为1，相同为0）
assign Cout = A & B;  // 进位 = A与B（均为1时进位1）

endmodule

src/combinational/full_adder.v
// 1位全加器（Full Adder）
// 功能：计算A + B + Cin，输出和S与进位Cout
module full_adder (
    input  wire A,    // 1位加数
    input  wire B,    // 1位加数
    input  wire Cin,  // 进位输入（区别于半加器的关键）
    output wire S,    // 和输出
    output wire Cout  // 进位输出
);

// 中间信号：连接两个半加器的临时结果
wire s_temp;  // 第一个半加器的"和"输出（A⊕B）
wire c1;      // 第一个半加器的进位输出（A&B）
wire c2;      // 第二个半加器的进位输出（(A⊕B)&Cin）

// 第1个半加器：计算A + B，得到临时和s_temp与进位c1
half_adder ha1 (
    .A(A),
    .B(B),
    .S(s_temp),  // 输出A⊕B
    .Cout(c1)    // 输出A&B
);

// 第2个半加器：计算s_temp + Cin，得到最终和S
half_adder ha2 (
    .A(s_temp),  // 输入为第一个半加器的"和"
    .B(Cin),
    .S(S),       // 最终和：A⊕B⊕Cin
    .Cout(c2)    // 输出(A⊕B)&Cin
);

// 或门：合并两个进位，得到最终进位输出Cout
assign Cout = c1 | c2;  // 等价于(A&B) | ((A⊕B)&Cin)

endmodule

tb/combinational/tb_full_adder.sv
// 全加器测试文件（SystemVerilog）
// 测试目标：验证所有8种输入组合下的S和Cout是否正确
module tb_full_adder;
    // 输入信号（用logic类型，自动推断为reg）
    logic A, B, Cin;
    // 输出信号（观测DUT的输出）
    logic S, Cout;

    // 实例化被测模块（DUT）
    full_adder dut (
        .A(A),
        .B(B),
        .Cin(Cin),
        .S(S),
        .Cout(Cout)
    );

    // 1. 波形生成配置（复用项目路径）
    initial begin
        $dumpfile("./waves/tb_full_adder.vcd");  // 波形文件路径
        $dumpvars(0, tb_full_adder);             // 记录所有层级信号
    end

    // 2. 测试激励与自动验证
    initial begin
        $display("=== 全加器测试开始 ===");
        $display("A | B | Cin | 预期S | 实际S | 预期Cout | 实际Cout | 结果");
        $display("--------------------------------------------------------");

        // 用循环遍历所有8种输入组合（3位二进制数0~7）
        for (int i = 0; i < 8; i++) begin
            // 拆分i为3位：A=最高位，B=中间位，Cin=最低位
            {A, B, Cin} = i;  // 例如i=3 → 二进制11 → A=0,B=1,Cin=1（因3位不足，高位补0）
            #10;  // 等待10ns，让信号稳定

            // 调用验证函数，传入预期结果
            check_result(
                A ^ B ^ Cin,                // 预期S = A⊕B⊕Cin
                (A & B) | (Cin & (A ^ B))   // 预期Cout = (A&B)|(Cin&(A⊕B))
            );
        end

        $display("=== 全加器测试结束 ===");
        $finish;  // 终止仿真
    end

    // 3. 验证结果的函数（封装判断逻辑）
    function void check_result(logic exp_S, logic exp_Cout);
        $write("%0d | %0d |  %0d  |   %0d    |   %0d    |    %0d     |    %0d     | ",
               A, B, Cin, exp_S, S, exp_Cout, Cout);
        
        // 自动判断并打印PASS/FAIL
        if (S == exp_S && Cout == exp_Cout) begin
            $display("PASS");
        end else begin
            $display("FAIL");  // 失败时一目了然
        end
    endfunction

endmodule

sim/waves/tb_full_adder.vcd
$date
	Sun Sep 21 14:59:58 2025
$end
$version
	Icarus Verilog
$end
$timescale
	1s
$end
$scope module tb_full_adder $end
$var wire 1 ! S $end
$var wire 1 " Cout $end
$var reg 1 # A $end
$var reg 1 $ B $end
$var reg 1 % Cin $end
$scope function check_result $end
$var reg 1 & exp_Cout $end
$var reg 1 ' exp_S $end
$upscope $end
$scope module dut $end
$var wire 1 # A $end
$var wire 1 $ B $end
$var wire 1 % Cin $end
$var wire 1 " Cout $end
$var wire 1 ( s_temp $end
$var wire 1 ) c2 $end
$var wire 1 * c1 $end
$var wire 1 ! S $end
$scope module ha1 $end
$var wire 1 # A $end
$var wire 1 $ B $end
$var wire 1 * Cout $end
$var wire 1 ( S $end
$upscope $end
$scope module ha2 $end
$var wire 1 ( A $end
$var wire 1 % B $end
$var wire 1 ) Cout $end
$var wire 1 ! S $end
$upscope $end
$upscope $end
$scope begin $ivl_for_loop0 $end
$var integer 32 + i [31:0] $end
$upscope $end
$upscope $end
$enddefinitions $end
$comment Show the parameter values. $end
$dumpall
$end
#0
$dumpvars
b0 +
0*
0)
0(
x'
x&
0%
0$
0#
0"
0!
$end
#10
1!
1%
b1 +
0&
0'
#20
1(
1!
1$
0%
b10 +
1'
#30
1"
0!
1)
1%
b11 +
#40
0"
1!
0)
1#
0$
0%
b100 +
1&
0'
#50
1"
0!
1)
1%
b101 +
0&
1'
#60
0(
1*
0!
0)
1$
0%
b110 +
1&
0'
#70
1!
1%
b111 +
#80
b1000 +
1'
