src/combinational/pcie_endpoint.v
`timescale 1ns / 1ps

module pcie_endpoint(
    input         clk,
    input         rst_n,
    input [31:0]  tlp_data,
    input         tlp_valid,
    output reg [31:0] rsp_data,
    output reg       rsp_valid
);

// 配置空间寄存器
reg [15:0] vendor_id;
reg [15:0] device_id;
reg [15:0] bar0;

// 存储器（8个16位单元）
reg [15:0] mem [0:7];

// TLP字段解析
wire is_config = tlp_data[31];
wire is_write  = tlp_data[30];
wire [7:0] addr = tlp_data[23:16];
wire [15:0] wdata = tlp_data[15:0];

// 初始化
initial begin
    vendor_id = 16'h1234;
    device_id = 16'h5678;
    bar0 = 16'h0000;
    // 初始化存储器
    for(int i=0; i<8; i=i+1) begin
        mem[i] = 16'h0000;
    end
end

// 主逻辑
always @(posedge clk or negedge rst_n) begin
    if(!rst_n) begin
        rsp_data <= 32'h00000000;
        rsp_valid <= 1'b0;
    end else begin
        rsp_valid <= 1'b0;
        
        if(tlp_valid) begin
            if(is_config) begin
                // 配置空间访问
                if(is_write) begin
                    // 配置写
                    if(addr == 8'h10) begin
                        bar0 <= wdata;
                    end
                    rsp_data <= 32'h00000001; // 成功标志
                    rsp_valid <= 1'b1;
                end else begin
                    // 配置读
                    case(addr)
                        8'h00: rsp_data <= {vendor_id, device_id};
                        8'h10: rsp_data <= {16'h0000, bar0};
                        default: rsp_data <= 32'h00000000;
                    endcase
                    rsp_valid <= 1'b1;
                end
            end else begin
                // 存储器访问
                if(addr < 8) begin
                    if(is_write) begin
                        mem[addr] <= wdata;
                        rsp_data <= 32'h00000001;
                        rsp_valid <= 1'b1;
                    end else begin
                        rsp_data <= {16'h0000, mem[addr]};
                        rsp_valid <= 1'b1;
                    end
                end else begin
                    rsp_data <= 32'hDEADDEAD; // 地址错误
                    rsp_valid <= 1'b1;
                end
            end
        end
    end
end

endmodule

tb/combinational/pcie_endpoint_tb.sv
`timescale 1ns / 1ps

module pcie_endpoint_tb;

reg         clk;
reg         rst_n;
reg [31:0]  tlp_data;
reg         tlp_valid;
wire [31:0] rsp_data;
wire        rsp_valid;

// 实例化DUT
pcie_endpoint uut (
    .clk(clk),
    .rst_n(rst_n),
    .tlp_data(tlp_data),
    .tlp_valid(tlp_valid),
    .rsp_data(rsp_data),
    .rsp_valid(rsp_valid)
);

// 时钟生成（100MHz）
initial begin
    clk = 0;
    forever #5 clk = ~clk;
end

// 生成波形文件
initial begin
    $dumpfile("wave.vcd");
    $dumpvars(0, pcie_endpoint_tb);
end

// 测试序列（带PASS/FAIL判断）
initial begin
    tlp_data = 32'h00000000;
    tlp_valid = 1'b0;
    rst_n = 1'b0;
    
    // 复位
    #10;
    rst_n = 1'b1;
    #10;
    
    // 测试1: 读配置ID（预期0x12345678）
    $display("\n=== 测试1: 读配置ID ===");
    send_tlp(1'b1, 1'b0, 8'h00, 16'h0000);
    check_rsp(32'h12345678);  // 传入预期值
    
    // 测试2: 写BAR0（预期响应0x00000001）
    $display("\n=== 测试2: 写BAR0 ===");
    send_tlp(1'b1, 1'b1, 8'h10, 16'h1234);
    check_rsp(32'h00000001);
    
    // 测试3: 读BAR0（预期0x00001234）
    $display("\n=== 测试3: 读BAR0 ===");
    send_tlp(1'b1, 1'b0, 8'h10, 16'h0000);
    check_rsp(32'h00001234);
    
    // 测试4: 写存储器（预期响应0x00000001）
    $display("\n=== 测试4: 写存储器 ===");
    send_tlp(1'b0, 1'b1, 8'h02, 16'h5678);
    check_rsp(32'h00000001);
    
    // 测试5: 读存储器（预期0x00005678）
    $display("\n=== 测试5: 读存储器 ===");
    send_tlp(1'b0, 1'b0, 8'h02, 16'h0000);
    check_rsp(32'h00005678);
    
    #20;
    $display("\n===== 所有测试结束 =====");
    $finish;
end

// 发送TLP任务（保持不变）
task send_tlp;
    input        is_config;
    input        is_write;
    input [7:0]  addr;
    input [15:0] wdata;
begin
    @(posedge clk);
    tlp_data = {is_config, is_write, 6'h00, addr, wdata};
    tlp_valid = 1'b1;
    $display("发送TLP: 0x%h", tlp_data);
    @(posedge clk);
    tlp_valid = 1'b0;
end
endtask

// 新增：带预期值检查的响应判断任务
task check_rsp(input [31:0] expected);
begin
    while (!rsp_valid) @(posedge clk);  // 等待响应
    
    // 比较实际值与预期值
    if (rsp_data === expected) begin
        $display("响应检查: PASS (实际: 0x%h, 预期: 0x%h)", rsp_data, expected);
    end else begin
        $display("响应检查: FAIL (实际: 0x%h, 预期: 0x%h)", rsp_data, expected);
    end
end
endtask

endmodule

sim/wave.vcd
$date
	Wed Oct  8 17:28:40 2025
$end
$version
	Icarus Verilog
$end
$timescale
	1ps
$end
$scope module pcie_endpoint_tb $end
$var wire 1 ! rsp_valid $end
$var wire 32 " rsp_data [31:0] $end
$var reg 1 # clk $end
$var reg 1 $ rst_n $end
$var reg 32 % tlp_data [31:0] $end
$var reg 1 & tlp_valid $end
$scope module uut $end
$var wire 1 # clk $end
$var wire 1 $ rst_n $end
$var wire 32 ' tlp_data [31:0] $end
$var wire 1 & tlp_valid $end
$var wire 16 ( wdata [15:0] $end
$var wire 1 ) is_write $end
$var wire 1 * is_config $end
$var wire 8 + addr [7:0] $end
$var reg 16 , bar0 [15:0] $end
$var reg 16 - device_id [15:0] $end
$var reg 32 . rsp_data [31:0] $end
$var reg 1 ! rsp_valid $end
$var reg 16 / vendor_id [15:0] $end
$scope begin $ivl_for_loop0 $end
$var integer 32 0 i [31:0] $end
$upscope $end
$upscope $end
$scope task check_rsp $end
$var reg 32 1 expected [31:0] $end
$upscope $end
$scope task send_tlp $end
$var reg 8 2 addr [7:0] $end
$var reg 1 3 is_config $end
$var reg 1 4 is_write $end
$var reg 16 5 wdata [15:0] $end
$upscope $end
$upscope $end
$enddefinitions $end
$comment Show the parameter values. $end
$dumpall
$end
#0
$dumpvars
bx 5
x4
x3
bx 2
bx 1
b1000 0
b1001000110100 /
b0 .
b101011001111000 -
b0 ,
b0 +
0*
0)
b0 (
b0 '
0&
b0 %
0$
0#
b0 "
0!
$end
#5000
1#
#10000
0#
1$
#15000
1#
#20000
0#
b0 5
b0 2
04
13
#25000
1!
1*
1&
b10000000000000000000000000000000 %
b10000000000000000000000000000000 '
1#
#30000
0#
#35000
0!
b1001000110100 5
b10000 2
14
b10010001101000101011001111000 1
0&
1#
#40000
0#
#45000
1!
b10010001101000101011001111000 "
b10010001101000101011001111000 .
1)
b10000 +
b1001000110100 (
1&
b11000000000100000001001000110100 %
b11000000000100000001001000110100 '
1#
#50000
0#
#55000
0!
b0 5
04
b1 1
0&
1#
#60000
0#
#65000
1!
b1 "
b1 .
b1001000110100 ,
0)
b0 (
1&
b10000000000100000000000000000000 %
b10000000000100000000000000000000 '
1#
#70000
0#
#75000
0!
b101011001111000 5
b10 2
14
03
b1001000110100 1
0&
1#
#80000
0#
#85000
1!
b1001000110100 "
b1001000110100 .
0*
1)
b10 +
b101011001111000 (
1&
b1000000000000100101011001111000 %
b1000000000000100101011001111000 '
1#
#90000
0#
#95000
0!
b0 5
04
b1 1
0&
1#
#100000
0#
#105000
1!
b1 "
b1 .
0)
b0 (
1&
b100000000000000000 %
b100000000000000000 '
1#
#110000
0#
#115000
0!
b101011001111000 1
0&
1#
